django_phac_aspc_helpers-3.1.2.dist-info/licenses/LICENSE
phac_aspc/__init__.py
phac_aspc/rules.py
phac_aspc/vanilla.py
phac_aspc/django/__init__.py
phac_aspc/django/comma_separated_field.py
phac_aspc/django/excel.py
phac_aspc/django/fields.py
phac_aspc/django/admin/__init__.py
phac_aspc/django/admin/decorators/__init__.py
phac_aspc/django/admin/decorators/admin_decorators.py
phac_aspc/django/helpers/__init__.py
phac_aspc/django/helpers/apps.py
phac_aspc/django/helpers/jinja_dtl_interop_utils.py
phac_aspc/django/helpers/auth/__init__.py
phac_aspc/django/helpers/auth/backend.py
phac_aspc/django/helpers/auth/views.py
phac_aspc/django/helpers/jinja_utils/__init__.py
phac_aspc/django/helpers/jinja_utils/include_from_dtl.py
phac_aspc/django/helpers/locale/__init__.py
phac_aspc/django/helpers/locale/code.py
phac_aspc/django/helpers/locale/language.py
phac_aspc/django/helpers/locale/en_CA/LC_MESSAGES/django.mo
phac_aspc/django/helpers/locale/en_CA/LC_MESSAGES/django.po
phac_aspc/django/helpers/locale/fr_CA/LC_MESSAGES/django.mo
phac_aspc/django/helpers/locale/fr_CA/LC_MESSAGES/django.po
phac_aspc/django/helpers/logging/__init__.py
phac_aspc/django/helpers/logging/configure_logging.py
phac_aspc/django/helpers/logging/json_post_handlers.py
phac_aspc/django/helpers/logging/utils.py
phac_aspc/django/helpers/ready/__init__.py
phac_aspc/django/helpers/ready/ready.py
phac_aspc/django/helpers/static/phac_aspc_helpers/base.css
phac_aspc/django/helpers/static/phac_aspc_helpers/auth/buttons/ms-logo.svg
phac_aspc/django/helpers/static/phac_aspc_helpers/phac_logos/en-fr.svg
phac_aspc/django/helpers/static/phac_aspc_helpers/phac_logos/en-fr__dark.svg
phac_aspc/django/helpers/static/phac_aspc_helpers/phac_logos/en.svg
phac_aspc/django/helpers/static/phac_aspc_helpers/phac_logos/en__dark.svg
phac_aspc/django/helpers/static/phac_aspc_helpers/phac_logos/fr-en.svg
phac_aspc/django/helpers/static/phac_aspc_helpers/phac_logos/fr-en__dark.svg
phac_aspc/django/helpers/static/phac_aspc_helpers/phac_logos/fr.svg
django_phac_aspc_helpers-3.1.2.dist-info/METADATA
django_phac_aspc_helpers-3.1.2.dist-info/WHEEL
django_phac_aspc_helpers-3.1.2.dist-info/top_level.txt
django_phac_aspc_helpers-3.1.2.dist-info/RECORD
