Metadata-Version: 2.4
Name: django-phac_aspc-helpers
Version: 3.1.2
Summary: Set of helpers for Django used at PHAC-ASPC
Home-page: https://github.com/PHACDataHub/django-phac_aspc-helpers
Author: Luc Belliveau
Author-email: luc.belliveau@phac-aspc.gc.ca
License: MIT
Classifier: Environment :: Web Environment
Classifier: Framework :: Django
Classifier: Intended Audience :: Developers
Classifier: License :: OSI Approved :: MIT License
Classifier: Operating System :: OS Independent
Classifier: Programming Language :: Python
Classifier: Programming Language :: Python :: 3
Classifier: Programming Language :: Python :: 3 :: Only
Classifier: Programming Language :: Python :: 3.11
Classifier: Programming Language :: Python :: 3.13
Classifier: Topic :: Internet :: WWW/HTTP
Classifier: Topic :: Internet :: WWW/HTTP :: Dynamic Content
Classifier: Topic :: Software Development :: Localization
Requires-Python: >=3.11
License-File: LICENSE
Requires-Dist: Authlib>=1.2.0
Requires-Dist: Django>=5.0
Requires-Dist: django-modeltranslation==0.18.11
Requires-Dist: django-environ==0.11.2
Requires-Dist: django-axes[ipware]==6.1.1
Requires-Dist: django-structlog==8.1.0
Requires-Dist: rules==3.3
Dynamic: license-file
